smalldata/__init__.py
smalldata/counter.py
smalldata/extract.py
smalldata/groupby.py
smalldata-0.0.3.dist-info/LICENSE
smalldata-0.0.3.dist-info/METADATA
smalldata-0.0.3.dist-info/WHEEL
smalldata-0.0.3.dist-info/entry_points.txt
smalldata-0.0.3.dist-info/top_level.txt
smalldata-0.0.3.dist-info/RECORD
