Metadata-Version: 2.1
Name: smalldata
Version: 0.0.3
Summary: Unix Pipe Fittings For Data Science
Home-page: https://github.com/mvtango/smalldata
Author: Martin Virtel
Author-email: martin.virtel@gmail.com
License: UNKNOWN
Platform: UNKNOWN
Classifier: Programming Language :: Python :: 3
Classifier: License :: OSI Approved :: MIT License
Classifier: Operating System :: OS Independent
